getFamaFrenchFactors.py
getFamaFrenchFactors-0.0.5.dist-info/LICENSE.txt
getFamaFrenchFactors-0.0.5.dist-info/METADATA
getFamaFrenchFactors-0.0.5.dist-info/WHEEL
getFamaFrenchFactors-0.0.5.dist-info/top_level.txt
getFamaFrenchFactors-0.0.5.dist-info/RECORD
